<?xml version="1.0" encoding="UTF-8"?>
<mods xmlns:mods="http://www.loc.gov/mods/v3"
      xmlns:xlink="http://www.w3.org/1999/xlink"
      xmlns:xsi="http://www.w3.org/2001/XMLSchema-instance"
      xmlns="http://www.loc.gov/mods/v3">
   <titleInfo usage="primary" displayLabel="Common Name">
      <title>Magnolia Macrophylla Big Leaf Magnolia</title>
  </titleInfo>
   <originInfo>
      <dateCreated keyDate="yes" point="start">1976</dateCreated>
      <dateCreated point="end">1989</dateCreated>
  </originInfo>
   <typeOfResource>still image</typeOfResource>
   <relatedItem type="host">
      <location>
         <url displayLabel="Relation">http://lsu.louisianadigitallibrary.org/lsu-msw%3Acollection</url>
      </location>
      <titleInfo displayLabel="Digital Collection">
         <title>Native Flora of Louisiana - Watercolor drawings by Margaret Stones</title>
      </titleInfo>
  </relatedItem>
   <location>
      <physicalLocation authority="oclcorg" displayLabel="OCLC Member Symbol">LUU</physicalLocation>
      <physicalLocation displayLabel="Physical Location">Louisiana State University: LSU Libraries</physicalLocation>
      <url displayLabel="Institution Web Site">http://lib.lsu.edu</url>
      <holdingSimple>
         <copyInformation>
            <subLocation>Hill Memorial Library: Special Collections</subLocation>
         </copyInformation>
      </holdingSimple>
   </location>
   <accessCondition type="use and reproduction" displayLabel="Contact Information">E-mail lsudiglib@lsu.edu with questions or comments. See instructions for ordering reprints of this item here: http://www.lib.lsu.edu/special/services/duplication.html Mention the "Item number" or "Item URL" in your request. </accessCondition>
   <note type="preferred citation" displayLabel="Cite As">Native Flora of Louisiana: Watercolor Drawings by Margaret Stones, Louisiana Digital Library, Baton Rouge, La.</note>
   <identifier displayLabel="Migrated From" invalid="yes" type="uri">http://cdm16313.contentdm.oclc.org/cdm/singleitem/collection/MSW/id/276</identifier>
   <recordInfo>
      <recordOrigin>Transformed into MODS from extended Dublin Core by the LDL Development Team at Louisiana State University.</recordOrigin>
      <recordCreationDate>2008-02-07</recordCreationDate>
      <recordChangeDate>2017-02-02</recordChangeDate>
  </recordInfo>
   <extension>
      <CONTENTdmData>
         <alias>MSW</alias>
         <pointer>276</pointer>
         <dmGetItemInfo mimetype="application/json"
                        source="https://server16313.contentdm.oclc.org/dmwebservices/index.php?q=dmGetItemInfo/MSW/276/json"
                        timestamp="2017-02-02 15:27:18">{"title":"Magnolia Macrophylla Big Leaf Magnolia","scient":{},"family":{},"famila":{},"habita":{},"relate":{},"creato":{},"date":{},"coverb":{},"publis":{},"covera":{},"contri":{},"descri":{},"notes":{},"langua":{},"drawin":{},"physic":{},"format":{},"source":{},"catlog":{},"rights":{},"cite":"Native Flora of Louisiana: Watercolor Drawings by Margaret Stones, LOUISiana Digital Library, Baton Rouge, La.","catalo":{},"image":{},"imaga":{},"color":{},"extent":{},"imagb":{},"file":{},"hardwa":{},"digiti":{},"digita":{},"to":"E-mail lsudiglib@lsu.edu with questions or comments. See instructions for ordering reprints of this item here: http:\/\/www.lib.lsu.edu\/special\/services\/duplication.html Mention the \"Item number\" or \"Item URL\" in your request. ","identi":{},"object":{},"collec":"http:\/\/louisdl.louislibraries.org\/cdm4\/index_MSW.php?CISOROOT=\/MSW","type":"Image","fullrs":"Volume47\\1_ms0001_Magnolia Macrophylla Big Leaf Magnolia.tif","find":"276.jp2","dmaccess":{},"dmimage":{},"dmcreated":"2008-02-07","dmmodified":"2008-02-07","dmoclcno":{},"dmrecord":"276","restrictionCode":"1","cdmfilesize":"4564330","cdmfilesizeformatted":"4.35 MB","cdmprintpdf":"0","cdmhasocr":"0","cdmisnewspaper":"0"}</dmGetItemInfo>
      </CONTENTdmData>
  </extension>
</mods>
